[
  {
    "mainTitle": "得獎致詞 Acceptance Speeches",
    "mainList": [
      {
        "minorTitle": "得獎致詞 (待處理)",
        "minorList": [
          {
            "title": "text",
            "icon": ["image", "video", "slide", "website"],
            "content": "content"
          },
          {
            "title": "text2",
            "icon": ["image", "video", "slide", "website"],
            "content": "content2"
          }
        ]
      }
    ]
  },
  {
    "mainTitle": "科普 Popular Science",
    "mainList": [
      {
        "minorTitle": "科普 (待處理)",
        "minorList": [
          {
            "title": "跨領域餐會開場致詞-芝麻開門-語音技術的前世今生",
            "icon": ["image", "video", "slide", "website"],
            "content": "content"
          },
          {
            "title": "科學月刊 李琳山：很多中文語音輸入產品都用到我的研究成果，但我沒賺到任何錢",
            "icon": ["image", "video", "slide", "website"],
            "content": "content2"
          }
        ]
      } 
    ]
  },
  {
    "mainTitle": "研究或生涯回顧 Research and Career Review",
    "mainList": [
      {
        "minorTitle": "研究或生涯回顧 (待處理)",
        "minorList": [
          {
            "title": "text",
            "icon": ["image", "video", "slide", "website"],
            "content": "content"
          },
          {
            "title": "text2",
            "icon": ["image", "video", "slide", "website"],
            "content": "content2"
          }
        ]
      } 
    ]
  },
  {
    "mainTitle": "專題演講 Speeches",
    "mainList": [
      {
        "minorTitle": "國際會議演講",
        "minorList":
        [
          {
            "title": "Spoken Content Retrieval - Lattices and Beyond",
            "icon": ["image", "video", "slide", "website"],
            "content": "content"
          },
          {
            "title": "text2",
            "icon": ["image", "video", "slide", "website"],
            "content": "content2"
          }
        ]
      } 
    ]
  },
  {
    "mainTitle": "綜合性 Others",
    "mainList": [
      {
        "minorTitle": "信號與人生",
        "minorList":
        [
          {
            "title": "2016/06/24 信號與人生",
            "icon": ["image", "video", "slide", "website"],
            "content": "content"
          },
          {
            "title": "2013/06/10 信號與人生",
            "icon": ["image", "video", "slide", "website"],
            "content": "content2"
          },
          {
            "title": "2008/XX/XX 信號與人生",
            "icon": ["image", "video", "slide", "website"],
            "content": "content2"
          },
          {
            "title": "2006/XX/XX 信號與人生",
            "icon": ["image", "video", "slide", "website"],
            "content": "content2"
          },
          {
            "title": "2005/10/01 信號與人生",
            "icon": ["image", "video", "slide", "website"],
            "content": "content2"
          }
        ]
      },
      {
        "minorTitle": "媒體訪問",
        "minorList": [
          {
            "title": "2017/02/13 自由時報 星期專訪",
            "icon": ["image", "video", "slide", "website"],
            "content": "content"
          },
          {
            "title": "2016/08/17 輕舟已過萬重山",
            "icon": ["image", "video", "slide", "website"],
            "content": "content2"
          }
        ]
      }
    ]
  },
  {
    "mainTitle": "婚禮致詞 Wedding Speeches",
    "mainList": [
      {
        "minorTitle": "婚禮致詞 (待處理)",
        "minorList": [
          {
            "title": "2016.01.09 盧彥廷 王雅婷婚禮致詞",
            "icon": ["image", "video", "slide", "website"],
            "content": "content"
          },
          {
            "title": "text2",
            "icon": ["image", "video", "slide", "website"],
            "content": "content2"
          }
        ]
      } 
    ]
  }
]
